[{"title": "al-\u1e63an\u2018ah. shoghl. mashriq\u012b. zajal", "sections": [[["12", "y\u0101 muslim\u012bn qalb\u012b da\u2018\u0101n\u012b", "\u0101sh k\u0101n du\u2018\u0101h", "\u1e25att\u00e1 sakan f\u012bh al-ghar\u0101m"], ["12", "khashf al-\u1e93ib\u0101 laqad ram\u0101n\u012b", "\u1e6darf san\u0101h", "\u2018all al-fu\u2019\u0101d bi-al-saq\u0101m"], ["12", "wal\u0101 qawiyat namsak \u2018in\u0101n\u012b", "\u1e25\u012bn ar\u0101h", "h\u0101yim muh\u012bn bayn al-an\u0101m"]], [["8", "fahal lid\u0101\u2019\u012b min \u1e6dab\u012bb", "la\u2018allah yubr\u012b al-\u2018al\u012bl"]], [["12", "\u2018\u0101shiq mutayyamun ka\u2019\u012bb", "wajdun da\u2018\u0101h", "bayn al-an\u0101m \u1e63abbun qat\u012bl"]]], "type": "al-\u1e63an\u2018ah", "identifier": "y\u0101 muslim\u012bn qalb\u012b da\u2018\u0101n\u012b", "poem": "zajal"}, {"title": "al-\u1e63an\u2018ah. mashriq\u012b. zajal", "sections": [[["0", "tawsh\u012bya"], ["0", "ghaybatuk z\u0101datn\u012b ashw\u0101q", "w\u0101lman\u0101m r\u012btuh jaf\u0101n\u012b"], ["0", "lam yazal \u1e6dab\u2018\u012b ruqayyaq", "\u1e25att\u00e1 \u1e63\u0101r bi-al-\u1e25ubb f\u0101n\u012b"], ["0", "lam nazal \u1e6d\u016bl \u2018umr\u012b na\u2018shaq", "wal-mal\u012b\u1e25 r\u012btuh war\u0101n\u012b"]], [["0", "wal-ma\u1e25abbah bi-al-ma\u2018\u0101n\u012b", "wal-mil\u0101\u1e25 m\u0101 hum saw\u012by\u0101"], ["0", "\u2018aynay waqalb\u012b nashawn\u012b", "hum bi-ithnayn \u0101ttafq\u016b\u0101 \u2018alayy\u0101"]]], "type": "al-\u1e63an\u2018ah", "identifier": "tawsh\u012bya", "poem": "zajal"}, {"title": "al-\u1e63an\u2018ah. mashriq\u012b. zajal", "sections": [[["16", "m\u0101 al-ghar\u0101m il\u0101 bal\u012by\u0101", "a\u2018dhir\u016bn\u012b y\u0101 muq\u0101bil"], ["16", "ash\u2018alat n\u0101run qaw\u012by\u0101", "tarakat al-jism n\u0101\u1e25il"], ["12", "\u1e0dayfun\u0101 shibh al-thurayy\u0101", "\u1e25ubbuh f\u012b al-qalb \u1e25\u0101\u1e63il"]], [["8", "shafruh k\u0101lssayf yaq\u1e6da\u2018", "bi-al-sih\u0101m laqad ram\u0101n\u012b"], ["16", "bi-al-wi\u1e63\u0101l l\u0101 zilt a\u1e6dma\u2018", "\u1e6d\u016bl \u2018umr\u012b wazam\u0101n\u012b"]]], "type": "al-\u1e63an\u2018ah", "identifier": "m\u0101 al-ghar\u0101m il\u0101 bal\u012by\u0101", "poem": "zajal"}]