[{"title": "al-\u1e63an\u2018ah. shoghl. \u1e25ij\u0101z kab\u012br. tawsh\u012b\u1e25 hazaj", "sections": [[["8", "lillah yawmun \u2018amman\u0101", "f\u012bh al-tah\u0101n\u012b wal-sur\u016br"], ["8", "in\u1e0damm f\u012bh shamlun\u0101", "niln\u0101 al-am\u0101n\u012b wal-\u1e25ub\u016br"], ["8", "ma\u2018 sh\u0101dinin \u1e25lw al-than\u0101", "yas\u1e6d\u016b \u2018al\u00e1 kull al-bud\u016br"]], [["8", "bi-al-khadd wal-qadd al-qaw\u012bm", "wal-thaghr durrun f\u012b \u0101nti\u1e93\u0101m"], ["8", "wal-sha\u2018r k\u0101lllayl al-bah\u012bm", "wal-wajh \u1e63ub\u1e25un f\u012b \u0101btis\u0101m"]]], "type": "al-\u1e63an\u2018ah", "identifier": "lillah yawmun \u2018amman\u0101", "poem": "tawsh\u012b\u1e25"}, {"title": "al-\u1e63an\u2018ah. \u1e25ij\u0101z kab\u012br. qa\u1e63\u012bdah. munsari\u1e25", "sections": [[["8", "a\u1e25sant y\u0101 layl f\u012b ta\u2019allufin\u0101", "bi-al-lah y\u0101 layl \u1e6dul wazid wazid"], ["8", "asa\u2019t y\u0101 \u1e63ub\u1e25 f\u012b tafarruqin\u0101", "bi-al-lah y\u0101 \u1e63ub\u1e25 tub wal\u0101 ta\u2018ud"]]], "type": "al-\u1e63an\u2018ah", "identifier": "a\u1e25sant y\u0101 layl f\u012b ta\u2019allufin\u0101", "poem": "qa\u1e63\u012bdah"}, {"title": "al-\u1e63an\u2018ah. shoghl. \u1e25ij\u0101z kab\u012br. tawsh\u012b\u1e25 l\u0101bin sahil", "sections": [[["13", "laylun \u2018aj\u012bb", "m\u0101 k\u0101n a\u1e25l\u0101h"], ["13", "gh\u0101b al-raq\u012bb", "l\u0101 raddah al-lah"], ["13", "wajh al-\u1e25ab\u012bb", "y\u0101 sa\u2018d man r\u0101h"]], [["4", "badr al-tam\u0101m", "qad hayyaj ashj\u0101n\u012b"], ["13", "yaq\u1e0d\u012b huy\u0101m", "lil\u2018\u0101shiq al-f\u0101n\u012b"]]], "type": "al-\u1e63an\u2018ah", "identifier": "laylun \u2018aj\u012bb", "poem": "tawsh\u012b\u1e25"}, {"title": "al-\u1e63an\u2018ah. \u1e25ij\u0101z kab\u012br. zajal", "sections": [[["14", "mahm\u0101 naltaq\u012b dh\u0101 al-shar\u016bd", "yalw\u012b \u1e6darfah al-s\u0101\u1e25ir"], ["14", "qult y\u0101 hil\u0101l al-su\u2018\u016bd", "y\u0101 badr al-duj\u0101 al-n\u0101\u2019ir"], ["9", "ta\u2018a\u1e6d\u1e6daf \u2018alayy\u0101 wajud", "wakun f\u012b al-kar\u00e1 z\u0101\u2019ir\u012b"]], [["10", "ir\u1e25am y\u0101 mal\u012b\u1e25 muhjat\u012b", "wasirr\u012b \u2018ayiyat nakhtaf\u012bh"], ["14", "y\u0101 r\u016b\u1e25\u012b way\u0101 r\u0101\u1e25\u1e25at\u012b", "\u2018\u0101lij biwi\u1e63\u0101lak watih"]]], "type": "al-\u1e63an\u2018ah", "identifier": "mahm\u0101 naltaq\u012b dh\u0101 al-shar\u016bd", "poem": "zajal"}, {"title": "al-\u1e63an\u2018ah. \u1e25ij\u0101z kab\u012br. tawsh\u012b\u1e25 mujtathth", "sections": [[["8", "al-layl laylun \u2018aj\u012bbun", "gharr \u1e6dalq al-mu\u1e25ayy\u0101"], ["8", "qad z\u0101r f\u012bh al-\u1e25ab\u012bb", "\u1e25ayy\u0101 al-fu\u2019\u0101d fa\u2019a\u1e25y\u0101"], ["8", "bihinn \u2018ayshun kha\u1e63\u012bbun", "\u1e25ayth \u0101irtashafn\u0101 al-\u1e25umayy\u0101"]], [["8", "wa\u1e25uzt a\u2018l\u0101 maq\u0101min", "walam nazal f\u012b \u0101nishir\u0101\u1e25"], ["8", "washamlun\u0101 f\u012b \u0101inti\u1e93\u0101min", "\u2018al\u00e1 zuh\u016br al-bi\u1e6d\u0101\u1e25"]]], "type": "al-\u1e63an\u2018ah", "identifier": "al-layl laylun \u2018aj\u012bbun", "poem": "tawsh\u012b\u1e25"}, {"title": "al-\u1e63an\u2018ah. \u1e25ij\u0101z kab\u012br. bas\u012b\u1e6d", "sections": [[["16", "waz\u0101\u2019irin z\u0101r f\u012b laylin faqult lah", "annast mustaw\u1e25ishan l\u0101 dhuqt m\u0101 dh\u0101q"], ["16", "wa\u1e63ilt mukta\u2019iban \u1e25all al-ghar\u0101m bih", "hlan biman lam yakhun \u2018ahdan wam\u012bth\u0101q\u0101"]]], "type": "al-\u1e63an\u2018ah", "identifier": "waz\u0101\u2019irin z\u0101r f\u012b laylin faqult lah", "poem": "unidentified"}, {"title": "al-\u1e63an\u2018ah. \u1e25ij\u0101z kab\u012br. zajal", "sections": [[["12", "ar\u00e1 al-lawz min ba\u2018d al-mash\u012bb", "y\u0101 \u1e63\u0101\u1e25 raja\u2018 luh al-shab\u0101b"], ["12", "waf\u0101\u1e25 niw\u0101run \u2018aj\u012bb", "nusaymah wa\u1e25a\u1e6d\u1e6d al-niq\u0101b"], ["8", "wal-khayl\u012b bithaghrin shan\u012bb", "ya\u1e0d\u1e25ak min buk\u0101\u2019 al-sa\u1e25\u0101b"]], [["8", "lilnnarjis \u2018uy\u016bn tandabil", "\u2018alayhim shu\u1e25\u016bb na\u1e93rat\u012b"], ["12", "h\u0101t al-r\u0101\u1e25 yud\u0101w\u012b al-thamal", "ta\u1e25l\u00e1 wata\u1e6d\u012bb ma\u2018ak s\u0101\u2018at\u012b"]]], "type": "al-\u1e63an\u2018ah", "identifier": "ar\u00e1 al-lawz min ba\u2018d al-mash\u012bb", "poem": "zajal"}]